{
  "annotations": {
    "changelogDate": "20260215213334"
  },
  "applications": "*",
  "dto": "mapstruct",
  "fields": [
    {
      "fieldName": "chunkIndex",
      "fieldType": "Integer",
      "fieldValidateRules": ["required"]
    },
    {
      "fieldName": "chunkText",
      "fieldType": "TextBlob",
      "fieldValidateRules": ["required"]
    },
    {
      "fieldName": "embeddingModel",
      "fieldType": "String"
    }
  ],
  "name": "DocumentChunk",
  "pagination": "no",
  "relationships": [
    {
      "otherEntityName": "document",
      "relationshipName": "document",
      "relationshipSide": "left",
      "relationshipType": "many-to-one",
      "relationshipValidateRules": "required"
    }
  ],
  "searchEngine": "no",
  "service": "serviceClass"
}
